[
	{
		"id": "1475232350141181952",
		"text": "@LizzVo Thank you. Not sure what I did but I will take it."
	},
	{
		"id": "1488561572393881606",
		"text": "Threats to kill \ud83d\ude33 https://t.co/eJ359u1fAJ"
	},
	{
		"id": "1488232536111210496",
		"text": "Loved this video on zero-knowledge proofs: https://t.co/MSmfqWh1VE"
	},
	{
		"id": "1479859120253538305",
		"text": "My son just told me that Maui ate his dinosaurs and coffee for breakfast. Three is a magical age."
	},
	{
		"id": "1277937106094977029",
		"text": "RT @nailainayat: After a court hearing Huma's mother Nagina Younas asks, should Christian mothers kill their daughters if conversion and ki\u2026"
	},
	{
		"id": "1468959052491223043",
		"text": "@ManavPande1 @CricNeelabh He didn't because team politics not only betrayed him but to nation also."
	},
	{
		"id": "1488621451829723137",
		"text": "RT @ProjectLincoln: A free sign-up to meet Donald Trump?\n\nYou know what to do\u2026 https://t.co/LTW0MpWjXK"
	},
	{
		"id": "1478057589149626369",
		"text": "RT @WizMonifaaa: I\u2019m not accepting weird friendships or people acting weird towards me in this new year. I\u2019ll never talk to u again."
	},
	{
		"id": "705447857403400193",
		"text": "@jayy_belle send me a pic of it"
	},
	{
		"id": "1024988027641376768",
		"text": "RT @Samvirke: \u00bbOm fem \u00e5r er der ikke nogen, der ejer sin egen bil mere, og de biler, vi k\u00f8ber nu, er de sidste,\u00ab siger \u2066\u2066@ClausSkytte\u2069. L\u00e6s\u2026"
	},
	{
		"id": "1474434874383736844",
		"text": ".@BBCR1 #Boris4Xmasno1"
	},
	{
		"id": "1488679714248183811",
		"text": "RT @CaseyNewton: I wrote about the revival of the EARN IT Act, which is bad and should go away\n\nhttps://t.co/bwDsoAUTRU https://t.co/69zkjU\u2026"
	},
	{
		"id": "1309209077419966464",
		"text": "That's a bunch of \"fucks\", but I'm in a rush to sign out of here and go have lunch with Kristina and the cats.\n\nSee you on the other side, I hope."
	},
	{
		"id": "1482067650905886725",
		"text": "RT @swplgbt: We are running a survey to help us better understand how we can best support our LGBTQ+ communities \ud83c\udff3\ufe0f\u200d\ud83c\udf08\ud83c\udff3\ufe0f\u200d\u26a7\ufe0f \n\nThe survey is\u2026"
	},
	{
		"id": "1485384787560910851",
		"text": "RT @catturd2: Get your congitive test."
	},
	{
		"id": "1485712403828404224",
		"text": "@Darkmage54 @AnkerOfficial Yes, log in with the same shared credentials on both phones."
	},
	{
		"id": "316340130577256448",
		"text": "Going running yeah for workout"
	},
	{
		"id": "1478414876284387329",
		"text": "@sara No Kidding...and kids could stay out without parents just as long as they were home when the street lights came on (at least that was the rule in Nebraska and Kansas back in the day)."
	},
	{
		"id": "1071252123055087616",
		"text": "RT @AltaJournal: Alta Magazine is pleased to support @826valencia + @826LA, a nonprofit organization dedicated to supporting under-resource\u2026"
	},
	{
		"id": "970121846220705797",
		"text": "#Truth https://t.co/a9PZSJ2WQu"
	},
	{
		"id": "1478108964000727040",
		"text": "Remember when lice was the worst thing kids could bring home? I miss those days. https://t.co/ORyTvt71yS"
	},
	{
		"id": "1488620125356019712",
		"text": "one person followed me and one person unfollowed me // automatically checked by https://t.co/3fHNWXfy1u"
	},
	{
		"id": "1479839712001118212",
		"text": "@BaronDavis I read a story recently about when he asked you and  @DaTrillStak5  to captain the team at Smitty\u2019s dive bar on Grand in Oakland over shots. Would\u2019ve loved to have been a fly on that wall."
	},
	{
		"id": "1479465318263054339",
		"text": "@rafat Could have and still could buy @skift - HNY sir."
	},
	{
		"id": "1488349394340622340",
		"text": "RT @TechAmazing: When history meets technology. https://t.co/9kuaFf9ws7"
	},
	{
		"id": "1486965280400379905",
		"text": "RT @Chooch_AI: Join us on 02/08. Learn how #ComputerVision is transforming the world. Register for free: https://t.co/MUAhxzjObN\n\n@CocaCola\u2026"
	},
	{
		"id": "1319050762970927105",
		"text": "RT @eobandosura: Presidente @IvanDuque Res#2370 ANLA que autoriza extracci\u00f3n de especies de aves, mariposas y ranas para zoo cr\u00eda es un abs\u2026"
	},
	{
		"id": "1039204802566049792",
		"text": "RT @BBGVisualData: Each map in this story shows the rise \u2191 or fall \u2193 in percentage terms of a county\u2019s total acreage devoted to corn, soybe\u2026"
	},
	{
		"id": "774354607237496832",
		"text": "I just completed @getmimo\u2019s quiz on Variables with 8/8 points. Can you beat my score? https://t.co/CtbKL6topX"
	},
	{
		"id": "1134406911976017921",
		"text": "ODESZA, Palo Alto, CA: Register for Presale Access &amp; WIN Meet &amp; Greet with ODESZA + more!: https://t.co/2yu9e2LzuW"
	},
	{
		"id": "1484578075115413509",
		"text": "@seldo Just show up one time like \"sup\"? Might get them to take you off the list"
	},
	{
		"id": "1488323444135530498",
		"text": "Holy smokes but some kind of confirmation/help ticket would be helpful"
	},
	{
		"id": "1357876655415586816",
		"text": "@elliotgilfix @cnnbrk Exactly..."
	},
	{
		"id": "1488621777211338759",
		"text": "RT @McHenryJD: The Gilded Age needs to case Jane Krakowski in character as Jenna Maroney playing a character in The Gilded Age"
	},
	{
		"id": "1445579405514870796",
		"text": "Nice piece featuring the amazing Dr. David Spiegel. My co-founder at https://t.co/lwNZLTey9c. #hypnosisworks. #reverihealth.  https://t.co/RIo70bFDta"
	},
	{
		"id": "1487443009708773381",
		"text": "@lindsey @BaskinEng Congratulations!"
	},
	{
		"id": "484089824136404992",
		"text": "#BELvsUSA #howard"
	},
	{
		"id": "1487443009708773381",
		"text": "@lindsey @BaskinEng Congratulations!"
	},
	{
		"id": "1216535876685066241",
		"text": "@meganphelps And on a lighter note, I feel like you and @DrunkBibleCast should totally be friends."
	},
	{
		"id": "1488636542889435136",
		"text": "Drinking a Bourbon County Brand Fourteen Stout (2021) by @GooseIsland @ 3rd Planet Brewing - The Mothership \u2014 https://t.co/kLuXQq4NAE"
	},
	{
		"id": "534103972773371904",
		"text": "@leleadani uomo vero, oltre che persona professionale e preparata!!!"
	},
	{
		"id": "992538303240032256",
		"text": "@cans4da Sentido Rio?"
	},
	{
		"id": "681051756311232512",
		"text": "burcuozberk'in foto\u011fraf\u0131 https://t.co/SJod1X7zMr"
	},
	{
		"id": "1436172164550496259",
		"text": "https://t.co/YqZeLKA8QG"
	},
	{
		"id": "1488691071173500931",
		"text": "Congrats https://t.co/TsU07F59C0"
	},
	{
		"id": "4917274052",
		"text": "@maryclare123 eu num gosto de crep\u00fasculo n\u00e3o!"
	},
	{
		"id": "1488664961748541441",
		"text": "RT @arilevine: When my great grandfather immigrated here to the US (1930 pre- Holocaust) his Certificate of Citizenship was very clear as t\u2026"
	},
	{
		"id": "1488607369097588736",
		"text": "Caveat: I take my phone to bed because I'm not a perfectly optimized person. But I plug it in, put it down, and pick up a physical book right away."
	},
	{
		"id": "1474811622761762819",
		"text": "xmas morning with Halo and she not in the mood. \ud83c\udf84\ud83d\udc36 https://t.co/WTO8fWnDA4"
	},
	{
		"id": "1325943622995505155",
		"text": "I was too tired to tweet about the TriNation game between NZ and AU once again. Have to hand it to the Wallabies. They really brought it. Hard fought and hard won. We'll get them next time. On to Argentina!"
	},
	{
		"id": "1480724351670390787",
		"text": "@dkathunt Constraints enable creativity."
	},
	{
		"id": "148440870952247297",
		"text": "PS Vita\u304b\u3089\u6295\u7a3f\u30c6\u30b9\u30c8\u3067\u3059\u3002"
	},
	{
		"id": "8739033645",
		"text": "omg havent been on this in ages haha and i havent a clue what to say :P"
	},
	{
		"id": "1470602613662130178",
		"text": "RT @NYDailyNews: \u201cWe hear rape jokes and sexual assault jokes ... left and right ... nothing is being done about it,\u201d said 13-year-old Esme\u2026"
	},
	{
		"id": "1488587338188046351",
		"text": "Today, I listen to a new track like \u201cCorridors of Power\u201d, LOUD, and think - this is as good as anything. Thank you @WarehamDean https://t.co/AF8oWdYqG8"
	},
	{
		"id": "1488000475412807682",
		"text": "\"Misinformation is a complex problem. Technology, governments, science institutions, educators and the public all have a part to play in assuring the quality of scientific information that underpins so much of our day-to-day lives.\"\n\nhttps://t.co/bu7oCpQCe5 https://t.co/pxiYykAZss"
	},
	{
		"id": "1488688848200605696",
		"text": "@om Shine on you crazy diamond..."
	},
	{
		"id": "578878920679882752",
		"text": "Siiiiii jaja @katyperry"
	},
	{
		"id": "1483494039483600896",
		"text": "RT @BUicinMezunlar: Okula giderken bilboardlar\u0131m\u0131z kar\u015f\u0131s\u0131n\u0131za \u00e7\u0131kabilir!\n\n\u00d6zg\u00fcr, \u00f6zerk ve demokratik \u00fcniversite i\u00e7in t\u00fcm bile\u015fenler olarak\u2026"
	},
	{
		"id": "1352323316984410113",
		"text": "Join me in supporting the Anpetu Wi wind farm @SageSRST https://t.co/hDqFdM6FIs"
	},
	{
		"id": "1488485278612348932",
		"text": "@brianslionsblog At first I was surprised by @TheRock\u2019s support for Rogan , but then I realized that he is exactly the type of person who would 1) Take advice from a meathead. 2) Take any opportunity to promote his horrible tequila."
	},
	{
		"id": "1487059099003101188",
		"text": "RT @shashashasha: That there is a Starship Enterprise implies the existence of a Starship Pro and a Starship Free"
	},
	{
		"id": "237608670119219200",
		"text": "@cassiorvidal Exemplo de hoje, orgulho de amanh\u00e3. \u2665"
	},
	{
		"id": "1486423630099718150",
		"text": "@sandys https://t.co/fxOz0FDwJT"
	},
	{
		"id": "1460313367478894592",
		"text": "@panic Any chance of this becoming a feature at some point?  I really like to distinguish my different projects by different themes."
	},
	{
		"id": "1134982182710042624",
		"text": "Epic gender reveal! Congrats Chuy and Abby cc @CieloHillsRanch https://t.co/L0Fy6FXyWm"
	},
	{
		"id": "1484573961023373319",
		"text": "Left Very a 1 star via @Trustpilot (https://t.co/HbDYJq8uL3) - They responded asking for my phone number to \"put things right\", never called. TLDR: They sent me an empty box for a \u00a3200 running watch, nearly 3 weeks later .. still not received a refund - @verynetwork @VeryHelpers"
	},
	{
		"id": "1488693265306062849",
		"text": "RT @rebeccanagle: Native Nations reach $590 million settlement with opioid manufacturers and distributers for their role in the opioid cris\u2026"
	},
	{
		"id": "1485885159882821640",
		"text": "Vandaag 25 januari: Dag van de ode aan de zorg! Breng jij een ode uit via social media met #odeaandezorg, aan een zorgcollega die een hart onder de riem verdient, aan een specifieke zorgorganisatie, of aan de zorg in het algemeen?! https://t.co/VzNI2lYpDT"
	},
	{
		"id": "1054459200363843586",
		"text": "Damn @AlaskaAir, it's glaringly obvious that when you acquired @VirginAmerica the first people you let go was the cust service staff. Long lines for in person support shouldn't take over 45 min and feel as cold as ice. #disappointed"
	},
	{
		"id": "1481121919684341763",
		"text": "@leepnet These days $500k is just friends and family. Still have many millions to go :)"
	},
	{
		"id": "1488694958249119744",
		"text": "\u8208\u5473\u6df1\u3044\u304a\u8a71\u3060\u3063\u305f\u3002"
	},
	{
		"id": "1454114808681410566",
		"text": "@MereTravels @onepeloton I \u2764\ufe0f Cody but I 100% approve of this decision"
	},
	{
		"id": "263753572469059584",
		"text": "$102.82 this week! This is how I now make a part time income... You can too &gt;&gt; http://t.co/oKFe4WSo"
	},
	{
		"id": "1486548390070550531",
		"text": "RT @christinevans: Today\u2026 a (maskless) @SFPD officer fails to remove DPW worker who has just *shoved* a guy and instead continues (with glo\u2026"
	},
	{
		"id": "1488718814988718081",
		"text": "RT @matt_merkle: Web 3.0 was clearly rushed, there's so many bugs. All we needed were higher quality cat videos and expanded pronoun manage\u2026"
	},
	{
		"id": "596038986352566272",
		"text": "wow...very beautiful https://t.co/FD1r0LVaTV"
	},
	{
		"id": "1488292669407182848",
		"text": "@artnome Would you consider adding an RSS feed?"
	},
	{
		"id": "408967442958807040",
		"text": "RT @FelonyRT: 'Fast &amp; Furious 7' Producer -- Movie Will Have To Wait -- It's Time To Grieve http://t.co/ycEQ0DixFp"
	},
	{
		"id": "1430978849274318863",
		"text": "G\u00f6z ya\u015flar\u0131m\u0131n do\u011fum g\u00fcn\u00fc kulu olur mu?"
	},
	{
		"id": "883303492965761025",
		"text": "Hey @handy any coupon codes I can use on my purchase? https://t.co/ET1n0IIv54 via @couponfollow"
	},
	{
		"id": "1481010330163548160",
		"text": "Opening a coin laundry dedicated to only accepting them Madam Maya Angelou\u2019s??"
	},
	{
		"id": "1488688848200605696",
		"text": "@om Shine on you crazy diamond..."
	},
	{
		"id": "1270133434346848260",
		"text": "@BabyLex511 I asked myself the same question but only because the series finale was so terrible, it makes the other 179 episodes pointless lol"
	},
	{
		"id": "1485738359041449991",
		"text": "@BillyLooney6 @DomStarsiaPLL My man!"
	},
	{
		"id": "107551183341748225",
		"text": "I just made $612 today working a few hour from home  http://t.co/Z9aG1JX"
	},
	{
		"id": "1488589005570543617",
		"text": "@GarySambrook89 @BorisJohnson For a parody account, you need to make it more obvious this is a joke. Or else we all think you genuinely believe this liar pos is a good bloke."
	},
	{
		"id": "976933459754135552",
		"text": "@Caterina @Vassar Yes!  Liberal Arts is a great foundation for entrepreneurism.  Thank you @Vassar."
	},
	{
		"id": "501039676069666817",
		"text": "Bangsat!!"
	},
	{
		"id": "392865743575851008",
		"text": "okay maybe I'm done for the year"
	},
	{
		"id": "1488607369097588736",
		"text": "Caveat: I take my phone to bed because I'm not a perfectly optimized person. But I plug it in, put it down, and pick up a physical book right away."
	},
	{
		"id": "1303145911913197568",
		"text": "@OlyaKurylenko just watched \u201cThe Courier\u201d.  Nice work and an extremely fun movie.  Will there be a sequel"
	},
	{
		"id": "1487922754879950849",
		"text": "RT @OldTimeDC: Painter + educator Alma Thomas in her DC home studio, 1530 15th St., NW, in 1971 [via @museumcolumbus]: https://t.co/BJr7pa9\u2026"
	},
	{
		"id": "1488632730560651269",
		"text": "When you're between 1% and 2% compound monthly growth it doesn't feel as good as it used to.\n\nIt might be a stretch to call it a struggle. You're likely still growing faster than most established businesses your size.\n\nBut you rarely see other SaaS founders sharing those numbers."
	},
	{
		"id": "1486152158953226240",
		"text": "@josiahfitness being in a relationship. \ud83d\ude02"
	},
	{
		"id": "1486016707961384960",
		"text": "BIG news. Congratulations to the newly expanded @upsidefoods team! https://t.co/WHeQJVTLQ8"
	},
	{
		"id": "1487088285704990720",
		"text": "@deliboard @Sharkyl @MattHaneySF @chesaboudin @LondonBreed This is insanity. What happens when permissiveness changes underlying behaviors. Brazenness becomes the norm. Hard to go back."
	},
	{
		"id": "19787078618",
		"text": "What do you want to share?follow me on twitter @mizloui"
	},
	{
		"id": "1487883364388552711",
		"text": "Go God! https://t.co/c1va3Lnkht"
	},
	{
		"id": "255792654112157696",
		"text": "@BY__HWAYOUNG wkwk cheon"
	},
	{
		"id": "1481673491686559747",
		"text": "@rrmutt why isn\u2019t everything already this? like Repo Man \u201cBeer\u201d but computer generated sludge https://t.co/YwssSM2HPB"
	},
	{
		"id": "1461686325933924354",
		"text": "RT @kick1972: PAUL JOURNET - La for\u00eat des mal-aim\u00e9s #lapresseplus https://t.co/kbO0dqwKv8"
	},
	{
		"id": "1488608678374612993",
		"text": "This whole Crisis Text Line story is truly bizarre. The poor judgement involved boggles the mind. https://t.co/0Qp15aN1X2 https://t.co/XDJRZ8hN7R"
	},
	{
		"id": "472435561660039169",
		"text": "Kenapa babi jalannya selalu menunduk hayooo???ada yang tau???"
	},
	{
		"id": "1429935579584765958",
		"text": "RT @elonmusk: 100k terminals shipped!\nhttps://t.co/Q1VvqVmJ2i"
	},
	{
		"id": "368973355468066816",
		"text": "exit dulu twibiboys. chibi chibi, ha ha ha ha ha ha. see you babay;*&lt;33"
	},
	{
		"id": "1438034956874354690",
		"text": "@carobehr @VoltDeutschland Hans-G\u00fcnter Br\u00fcnker (Volt) \"Dabei muss zwangsl\u00e4ufig auch die Frage gestellt werden, inwiefern die Kassenvielfalt beibehalten werden soll.\" (https://t.co/XRjXtfoF1O) Ich glaube, bei Euch herrscht da noch keine Einigkeit ;-)"
	},
	{
		"id": "1451761193081659392",
		"text": "@wongJP There\u2019s my name. Before I stole your P."
	},
	{
		"id": "948845758396141569",
		"text": "\u05d0\u05d4\u05d5\u05d3 \u05d1\u05e8\u05e7 \u05d0\u05d5\u05dc\u05d9 \u05ea\u05ea\u05d7\u05d9\u05dc \u05dc\u05e1\u05ea\u05d5\u05dd \u05d0\u05ea \u05d4\u05e4\u05d4 \u05e9\u05dc\u05da! \u05d0\u05ea\u05d4 \u05d1\u05df \u05d0\u05d3\u05dd \u05d4\u05de\u05d9\u05d9\u05e6\u05e8 \u05e9\u05d9\u05e0\u05d0\u05d4 \u05d5\u05de\u05ea\u05d5\u05e1\u05db\u05dc \u05d0\u05dc \u05d3\u05d0\u05d2\u05d4 \u05e0\u05e1\u05ea\u05d3\u05e8 \u05d1\u05dc\u05e2\u05d3\u05d9\u05da."
	},
	{
		"id": "1309209077419966464",
		"text": "That's a bunch of \"fucks\", but I'm in a rush to sign out of here and go have lunch with Kristina and the cats.\n\nSee you on the other side, I hope."
	},
	{
		"id": "42317291924365312",
		"text": "RT @leehtorres2: to aki no col com o @castro_alote"
	},
	{
		"id": "11037",
		"text": "trying to hydrate after a long weekend of debotchery. some food is helping...more fluid...please"
	},
	{
		"id": "1486580954168643585",
		"text": "RT @karouisnotgone: Our hospital is full, our morgue is full, we are trying to run our ER with 2 RNs (\ud83d\ude4b\ud83c\udffd\u200d\u2640\ufe0f+ 1), I have bruises on my hands\u2026"
	},
	{
		"id": "91968891718348800",
		"text": "Screw workkk today :( I hate waking up in the rain - this news article is so motivational!! http://tinyurl.com/6ecsbu4"
	},
	{
		"id": "894847848918994944",
		"text": "@BandQ @bandq_help Just been told by the BandQ CS advisor that his computer is down and will be fixed this Friday #disappointed"
	},
	{
		"id": "1390178336350081027",
		"text": "RT @LibraTerms: The company of a #Libra is refreshing, fulfilling, often very enlightening &amp; highly sought after."
	},
	{
		"id": "1488561070738481158",
		"text": "@victorhvgo Haha eu amo uma banda &lt;3"
	},
	{
		"id": "1479859120253538305",
		"text": "My son just told me that Maui ate his dinosaurs and coffee for breakfast. Three is a magical age."
	},
	{
		"id": "447263929169756161",
		"text": "Good night\ud83d\ude34\ud83d\ude34\u270c"
	},
	{
		"id": "1481079654693982209",
		"text": "@ReeseW @juliaj sounds like we need to relaunch mEgo portable profiles :-) https://t.co/Dqvu6fOj51"
	},
	{
		"id": "1488544973486239750",
		"text": "@caesarowak @AirlineFlyer @flightradar24 @flyethiopian Till they got A350, they were an almost all Boeing fleet for many years and Douglas before it. (some MD-11 and De Havilland props inbetween)"
	},
	{
		"id": "1488566923474448384",
		"text": "RT @rihanna: introducing\u2026ICON!! @fentybeauty\u2019s new lipstick collection \ud83d\udc8b\ud83d\udc84a curated range of 10 bold reds &amp; classic nudes. https://t.co/jmVH\u2026"
	},
	{
		"id": "378675940261261312",
		"text": "I wish the twitter team the best of luck and trust that they will be successful in continuing to develop this important communication tool."
	},
	{
		"id": "1486539096214278144",
		"text": "@djschwin Wait do I need to watch \u201cJohn Wick\u201d before watching \u201cNobody?\u201d Because I don\u2019t have that kind of time."
	},
	{
		"id": "340235948946255872",
		"text": "Discovering new adventures with @TriplAgent. http://t.co/5vdml2V3qN"
	},
	{
		"id": "1480291436125990919",
		"text": "@evgrieve @LESDK3 Jane\u2019s is indeed a wonderful consignment shop! They focus on in-season and lightly-worn clothing, and I have bags of all-season and spring/ summer gear \u2026"
	},
	{
		"id": "1485689012077862912",
		"text": "@olyalo @Spotify Congratulations Olya!"
	},
	{
		"id": "1488702612224413697",
		"text": "RT @dunepod: We were lucky to have @Protolexus from the @70mmpod shed light on the complicated media landscape we live in, namely: how do w\u2026"
	},
	{
		"id": "205210028691558400",
		"text": "brings back old memories.. http://t.co/Yzf7NmxJ - the leh bike trip"
	},
	{
		"id": "1472480456537145344",
		"text": "RT @jplus_jigokurak: \uff0f\n\u3297\u30a2\u30cb\u30e1\u65b0\u60c5\u5831\u89e3\u7981\uff01\n#\u304a\u5f85\u305f\u305b\u3057\u307e\u3057\u305f\u5730\u7344\u697d\n\u30d5\u30a9\u30ed\u30fc\uff06RT\u30ad\u30e3\u30f3\u30da\u30fc\u30f3\ud83c\udf89\n\uff3c\n\n#\u8cc0\u6765\u3086\u3046\u3058 \u5148\u751f\u306e\u76f4\u7b46\u30a4\u30e9\u30b9\u30c8\u8272\u7d19\u3092\u62bd\u9078\u30671\u540d\u69d8\u306b\u30d7\u30ec\u30bc\u30f3\u30c8\uff01\n\n\u25a0\u5fdc\u52df\u65b9\u6cd5\n\u2460@jplus_jigokurak\u3092\u30d5\u30a9\u30ed\u30fc\n\u2461\u3053\u306e\u6295\u7a3f\u3092\u30ea\u30c4\u30a4\u30fc\u30c8\u2026"
	},
	{
		"id": "1353750467319361540",
		"text": "Jan 27, 2021 (7 PM - 9 PM) - Resources for Small Business Owners https://t.co/46hCvnJ2F8"
	},
	{
		"id": "1195399635914776576",
		"text": "My cat just did a retweet."
	},
	{
		"id": "112569125670363136",
		"text": "Or maybe it's just little boys"
	},
	{
		"id": "567677893749538816",
		"text": "Ganmamg style quetema mas chistoso ese video"
	},
	{
		"id": "1488447704254455810",
		"text": "\u5e73\u5747\u5e74\u9f62\u7d0435\u6b73 https://t.co/2hsF5m980j"
	},
	{
		"id": "1488605594730872832",
		"text": "The latest The Trendy Nic Daily! https://t.co/h68DfbnebV Thanks to @ManTripping #gno #timepoy"
	},
	{
		"id": "1488708491422408706",
		"text": "@JorBozo @LakeShowYo Lol you really think you did something huh smh"
	},
	{
		"id": "765372758511484928",
		"text": "Trump Taj Mahal's July revenue down while industry up in A.C. https://t.co/8E50la8BG6 via @PHLBizJournal"
	},
	{
		"id": "252424928333291521",
		"text": "\u30e2\u30a4\uff01\u30d1\u30bd\u30b3\u30f3\u304b\u3089\u30c4\u30a4\u30ad\u30e3\u30b9\u3067\u914d\u4fe1\u4e2d http://t.co/iXepIG9g"
	},
	{
		"id": "239503458867216384",
		"text": "Whats the name of this anti-war, anti-nwo band with the middle-eastern riffs? (live at http://t.co/dp6M1w3p)"
	},
	{
		"id": "572205167581380608",
		"text": "I challenged Wo Hao Niu Cha and won:) Challenge players from around the world! #BrainWars\nhttp://t.co/gGP7JZZcNd http://t.co/IrdBftRWW3"
	},
	{
		"id": "1488399912467255296",
		"text": "When we carried all of our possessions moving to New Zealand as luggage it felt like we had so much. Now that we\u2019re in a house it feels like almost nothing. Surreal."
	},
	{
		"id": "13010521",
		"text": "http://www.youtube.com/v/bm1VHIxZ96Q &lt;-- ufo attacks!"
	},
	{
		"id": "626945848639930368",
		"text": "http://t.co/xl1LraaGye"
	},
	{
		"id": "1484596477397590016",
		"text": "RT @GovofCO: If you\u2019re looking to upgrade your mask game and protect yourself, please visit and find a location near you: https://t.co/rkoS\u2026"
	},
	{
		"id": "1487110905234034695",
		"text": "Wordle 223 2/6\n\n\ud83d\udfe8\ud83d\udfe9\u2b1c\u2b1c\ud83d\udfe9\n\ud83d\udfe9\ud83d\udfe9\ud83d\udfe9\ud83d\udfe9\ud83d\udfe9 I\u2019m new. Is this how you do it?"
	},
	{
		"id": "107895321274757121",
		"text": "Hey everyone I made $386 today check out how I made it! http://t.co/vYidTGN"
	},
	{
		"id": "1485940172046880768",
		"text": "@SF_Moro N\u00e3o, desista"
	},
	{
		"id": "1488366299763732482",
		"text": "@linesthebear @Spotify Apple Music. \ud83e\udd37"
	},
	{
		"id": "1246057499922325504",
		"text": "So far I have seen real fighters on border to protect India... Now we have seen many real fighters inside India. Big salute to these fighters like Doctors, nurse, police, sweepers, media... This is called real INDIA. Thanks to all \ud83d\ude4f\ud83d\ude4f"
	},
	{
		"id": "385260611031924736",
		"text": "RT @sauroscompany: Universitarios crean un robot para buscar personas en zonas de desastre http://t.co/2CRWQ6CNbH"
	},
	{
		"id": "1488608491640168455",
		"text": "Break up to break out and break through!\nThis is where love and light meets shadow work. This shit can be easier and you can be happyAF. https://t.co/zbv4eI56ST"
	},
	{
		"id": "117419428160872449",
		"text": "On a date with a hot woman."
	},
	{
		"id": "273211031730417664",
		"text": "Making money from home has never been so easy... Working about 3 hours a day http://t.co/3JK2dIzd"
	},
	{
		"id": "1266109301325627392",
		"text": "Holy Shit, its still here!"
	},
	{
		"id": "1377375159384948739",
		"text": "@TeufeurSoff @joonsttv pour toi #RolexbyTeufeurS"
	},
	{
		"id": "1488513457054011399",
		"text": "RT @FaheemYounus: Have sore throat fever but rapid test is negative. What next?\n\nYou\u2019re likely COVID+. Do one of the following:\n\n1. Repeat\u2026"
	},
	{
		"id": "1488679259996446722",
		"text": "Growth is going from #therapy every week to every other week. \n#MentalHealthMatters #Mentalhealth"
	},
	{
		"id": "1483256863915397120",
		"text": "She\u2019s about 3 years old, and decided a couple of weeks ago to just move in. She\u2019s a sweet gal, so I guess she\u2019s staying \ud83e\udd37\ud83c\udffb\u200d\u2640\ufe0f\ud83d\ude02 https://t.co/kEiFWOPPjK"
	},
	{
		"id": "1488684859660795905",
		"text": "Hay una trabajadora de casa particular de subse y el sacoweas del cuico de Torrealba dice que al gobierno de Boric le falta calle.\nSon weones hasta cuando le dan servida la opci\u00f3n de no ser weones"
	},
	{
		"id": "1486675590828548096",
		"text": "@ICICIBank_Care how do I close a bank account in India, when I'm in Singapore, can I give the account closing request to a Singapore branch?"
	},
	{
		"id": "233241811831881728",
		"text": "http://t.co/yW8G2U5Z Ranitidine"
	},
	{
		"id": "1312001018452992002",
		"text": "Is this thing on?"
	},
	{
		"id": "255516699015655424",
		"text": "Kandy Korn! :) http://t.co/l36Aqcxn"
	},
	{
		"id": "449005151144009728",
		"text": "@pgm_ratinho #BotecDoRatinho"
	},
	{
		"id": "536343495519133696",
		"text": "78330: Severe Weather Statement issued November 22 at 8:17PM CST until November 22 at 8:45PM CST by NWS Corpus Christ http://t.co/CPB4np4G56"
	},
	{
		"id": "1264524758109974528",
		"text": "I can be a bitch, too, if I try to be"
	},
	{
		"id": "429979969691717633",
		"text": "\u041b\u0435\u0447\u0435\u043d\u0438\u0435 \u043a\u0430\u0440\u0438\u0435\u0441\u0430 \u0421\u0442\u0443\u0434\u0435\u043d\u0447\u0435\u0441\u043a\u0430\u044f http://t.co/lM2kf9Q0Kt"
	},
	{
		"id": "1488074765688524803",
		"text": "Discover #Europe as it blooms into colour with our Flowers and Gardens Holidays! A treat for the eyes, visit the renowned #KeukenhofPark or explore the incredible #FloriadeExpo \u2013 a once a decade event! Book your springtime escape today &gt; https://t.co/V7AeA72b5n https://t.co/kcJLxnkx2f"
	},
	{
		"id": "1406963224105259016",
		"text": "@WaveHQ @tksimpson I've been waiting 5 months for Wave support to follow up on some issues. I've emailed several times, but no movement. Can someone please make this a priority, it's very frustrating."
	},
	{
		"id": "1487685393105317889",
		"text": "@kentcdodds Glad to hear you\u2019re okay bud!!!"
	},
	{
		"id": "1488696881341419522",
		"text": "@whaleokay Ngl that looks good"
	},
	{
		"id": "1488410555324977152",
		"text": "Wordle 227 3/6*\n\n\u2b1b\u2b1b\ud83d\udfe8\u2b1b\ud83d\udfe8\n\ud83d\udfe9\u2b1b\u2b1b\ud83d\udfe9\ud83d\udfe9\n\ud83d\udfe9\ud83d\udfe9\ud83d\udfe9\ud83d\udfe9\ud83d\udfe9"
	},
	{
		"id": "1395870407442399232",
		"text": "Issues with my package deliveries from the @USPS. Countless occasions my package has being delivered to a similar/ wrong address.  Left notes &amp; spoke with the delivery person to help with this issue. Todays package was just left on top of the community mailbox @USPSHelp"
	},
	{
		"id": "1488664139224412161",
		"text": "RT @necrosofty: So @Roryfelton and @MCSerch of Third Bass appear to be the people in charge of @joinhitpiece, stealing music/selling it as\u2026"
	},
	{
		"id": "1488035015330091008",
		"text": "La trinitat impossible https://t.co/uOzNwS2EqS @frtarrago"
	},
	{
		"id": "451776678877233152",
		"text": "Young girls today are looking for trouble posting pics like this, she does not look older then 14 http://t.co/kY3q0lQfuK"
	},
	{
		"id": "1487755483754774531",
		"text": "Would you buy a home in the metaverse?\n https://t.co/wPlIt6lCEC https://t.co/vaY70foyWb"
	},
	{
		"id": "1323220947017629696",
		"text": "@WyvernLingo Please gib belfast gig!!!!"
	},
	{
		"id": "1109912930395389954",
		"text": "@SourPatchKids experienced grapefruit flavor and disappointed not to get it again in our next pack. Is this real?! So much better than orange!"
	},
	{
		"id": "1488140375122317312",
		"text": "*179th (Jan 2022) edition of eMagazine PreSense*\nEditorial on @narendramodi  breach of security  +   making of Indian Constitution  +  Exciting story of Arya Bhashyam who hoisted Indian tri-colour  on 26th Jan 1932\nhttps://t.co/rj4KlebIUe\n\n@arjunrammeghwal  @PriyaRahul_2020 https://t.co/JmOEUEgyFu"
	},
	{
		"id": "1475888008041623558",
		"text": "@typeamb Which one ?"
	},
	{
		"id": "1487563443771088896",
		"text": "Is there anything more unpatriotic than covering our lovely stars and bars with a deranged man-baby? \n\n[checks notes]\n\nYes, of course, my fault. Attacking our nation\u2019s capital because your man-baby didn\u2019t win is indeed more unpatriotic. https://t.co/5tXXtCXdur"
	},
	{
		"id": "1480805117334937600",
		"text": "@MalteseAnna Fascinating keepsake, further humanized by details like the torn brad holes and misspelling of \u201cdispensed\u201d in the last line of text. What a find!"
	},
	{
		"id": "1488683099676450817",
		"text": "Siento que estoy en julio de 2020 otra vez, que pesadilla."
	},
	{
		"id": "1473631682079166472",
		"text": "one person unfollowed me // automatically checked by https://t.co/wDRn8rePSU"
	},
	{
		"id": "1488715156246958081",
		"text": "@damnarbor I'll allow it.  But you also have to look at the hideous 70s (?) era apartments in the OWS to see how Blah this can be, and how bad the response can be (OWS Association is absurd). Is there a good inbetween?"
	},
	{
		"id": "1487893820180099072",
		"text": "@skamille happy birthday!"
	},
	{
		"id": "1433441752401289219",
		"text": "@PhillyPolice Or we'll shoot you. No wait, you're under arrest. I mean, can I see your ID? You can't be standing there, this is private property. Shut up or I'll tase you. You talkin' to me?"
	},
	{
		"id": "119127504941355009",
		"text": "@Mony_de_Swaan UNA GRAN MENTIRA!!! A MI CEL LE DESC EL TMPO D LA GRAB EN BUZON DE VOZ, D HECHO DICEN: LA LLAMADA SE COBR AL TERM LOS TONOS"
	},
	{
		"id": "1487036232118976519",
		"text": "This is prob the coolest thing I\u2019ve seen for back country skiing https://t.co/kGkPg3Nrgg prob something @johnv @sacca should know about."
	},
	{
		"id": "378675940261261312",
		"text": "I wish the twitter team the best of luck and trust that they will be successful in continuing to develop this important communication tool."
	},
	{
		"id": "1487905419423014921",
		"text": "RT @Miss_Beehave8_: Starting in one hour. Raising money for @childrenscancer while playing some more #Fallout4 We hit our first milestone y\u2026"
	},
	{
		"id": "1038132835956273153",
		"text": "I just opened a mystery potion in Agario and won amazing rewards. Come and play to win unique mystery skins! https://t.co/GEMqMvwMqV"
	},
	{
		"id": "1429729295778394113",
		"text": "Selling 2 Leeds fest Sunday tickets dm #LeedsFestival"
	},
	{
		"id": "1435941055342522369",
		"text": "https://t.co/toc9g1JzJr \nWow."
	},
	{
		"id": "1488718492123680774",
		"text": "@neekscorrea \ud83e\udd23\ud83e\udd23\ud83e\udd23 https://t.co/VCXYwDwqKw"
	},
	{
		"id": "1468316087330775041",
		"text": "@mymoneyblog so wait... her daughter was less than a year old when \"The mother-daughter duo first launched Pixie\u2019s Bows in 2011\"?"
	},
	{
		"id": "1401452496724414464",
		"text": "@oillypen @Olurops @dazzleriri @akaneb @dondekojo The question to you is will there ever be that change you desire most for Nigeria? If yes, can you imagine how this would unfold? If no, then we are just in cycles!"
	},
	{
		"id": "1488719324890091524",
		"text": "@BruceFeiler To me it\u2019s more about what Freud calls the narcissism of small differences. We can debate how stupid her comment is. We can\u2019t debate whether this is at all important in the grand scheme of things. It just clearly isn\u2019t."
	},
	{
		"id": "1488718814636384258",
		"text": "my mom had a debilitating case of tuberculosis in india, and she calls it her \"first pandemic\" https://t.co/02t7ZiVEuN"
	},
	{
		"id": "1451741213225328643",
		"text": "RT @AishaYesufu: Pastors will pray for the fruit of the womb but never for the fruit of the testicle!- Father Angelbert Chikere"
	},
	{
		"id": "1488500955549257728",
		"text": "Stop Being So SMART: A Reflection on Resiliency During the Time of COVID, Systemic Oppression, and Seasons of Love https://t.co/Cz779H2TlK"
	},
	{
		"id": "1488710616915263492",
		"text": "Ye look upon my takes and despair https://t.co/fX1B5Rh8We"
	},
	{
		"id": "577294975186165760",
		"text": "@WPXI @WPXIScott Valencia, PA! http://t.co/F8IbW42Ht9"
	},
	{
		"id": "118654509546340353",
		"text": "RT @ChicagoDrives: Why tolling on Chciago's Lake Shore Drive is a BAD idea:  http://t.co/WNIHQmDz"
	},
	{
		"id": "1470482871349559309",
		"text": "Looking for positive attitude and the \u201cnothing is impossible\u201d-mindset, look no further, see this documentary about @nimsdai and how he and his team claimed all 14 peaks over 8000m in 7mo. (My Everest and two others in 48h) https://t.co/cV7GM4UoRZ"
	},
	{
		"id": "1482516637186248709",
		"text": "RT @RezenGaming: Behold the worlds first ever TXT message sent about a Bengals playoff win. Congrats #bengals #NFLPlayoffs #NFL https://t.c\u2026"
	},
	{
		"id": "1475827138628669443",
		"text": "RT @MiamiDolphins: Waddle \ud83d\udc27\nWaddle \ud83d\udc27\n\n#FinsUp x #DolphinsElevator https://t.co/a4gaNGTBNI"
	},
	{
		"id": "1488150317829136390",
		"text": "Marc Benioff discusses his early career, Salesforce's beginnings, &amp; improving the state of the world on Guy Kawasaki's Remarkable People podcast. https://t.co/wbKheV8Yo4"
	},
	{
		"id": "1488636299842043905",
		"text": "@EmmySalamon This is now my favorite chain on Twitter https://t.co/4qCOupaFBV"
	},
	{
		"id": "1453913245366902784",
		"text": "@nolanb2 Super cool! Thanks! Last time I funded something on such a platform it was @BrianFargo and Wasteland 2. Fun party :)"
	},
	{
		"id": "1488651169631191046",
		"text": "it\u2019s @cordae https://t.co/eE2vNo9D3K"
	},
	{
		"id": "1488721480967876613",
		"text": "RT @THECULTCARDS: \ud83d\udea8Culture Cards x @dreamr_app Giveaway!!\ud83d\udea8\n\n\ud83d\udcb04 Culture Cards #NFTs + 250K $DMR to winners!\ud83d\udc8e\n\n\ud83e\udd471 Winner GOLD Big Pun NFT + 1\u2026"
	},
	{
		"id": "64678214819254272",
		"text": "@rirakumayo \u304a\u4ef2\u9593\u304c\u3044\u3066\u5fc3\u5f37\u3044\u3067\u3059(^-^)v\u3002\u671d\u30c4\u30e9\u3044\u306e\u306f\u3057\u3093\u3069\u3044\u3067\u3059\u306d\u3002\u3046\u3061\u306e\u3068\u3053\u3082\u65e6\u90a3\u306f\u4e0d\u5b9a\u4f11\u3067\u3001\u4f11\u307f\u304c\u8aad\u3081\u306a\u304f\u3066\u4e88\u5b9a\u7acb\u3066\u308c\u306a\u3044\u3063\u3059\u3088(&gt;_&lt;)\u3002\u304a\u4e92\u3044\u30c9\u30f3\u30de\u30a4\u3067\u3059\u306d\u3002"
	},
	{
		"id": "788504296954351616",
		"text": "#ABGT203 Another great start! And another commute that just got better. #fanforlife 12 years and counting!"
	},
	{
		"id": "436506219256094721",
		"text": "vagoty203011"
	},
	{
		"id": "934249632573648896",
		"text": "@regularcars I'm game"
	},
	{
		"id": "916356147585605632",
		"text": ".@POTUS and @DeptofJustice: This is SHAMEFUL! Anti-#LGBT guidance is an affront to American values. @equalityfed @realdonaldtrump"
	},
	{
		"id": "83702504214380544",
		"text": "I'm sooo not looking forward to getting up for work tomorrowwww - cant wait for this thing to work! http://tinyurl.com/6l4s4oa"
	},
	{
		"id": "25023959882",
		"text": "Driving aroundd :P"
	},
	{
		"id": "1488181141182070787",
		"text": "@Almanassa_AR \u0644\u064a\u0647 \u062a\u062c\u0627\u0647\u0644 \u0663\u0660 \u064a\u0648\u0646\u064a\u0648\u061f"
	},
	{
		"id": "242599272737030144",
		"text": "Started rehearsals of Mario O'Hara's STAGESHOW.  Mario was able to attendthe reading rehearsals before he passed away 2 months ago."
	},
	{
		"id": "1171888621214822400",
		"text": "amazing, took 13 years, but I just got access to my original twitter account back! @timroberts thanks for the early hookup!"
	},
	{
		"id": "1488699802632302601",
		"text": "RT @BAKKOOONN: abbotts been scootin around that border wall down there doing photo ops for 8 months and didnt fix this shit and its gonna h\u2026"
	},
	{
		"id": "1042495403088928769",
		"text": "Hello @yggtorrent_com , comment \u00e7a se passe pour l'URL du tracker ? les fichier torrent sont toujours en .is et donc impossible de s'annoncer sur le tracker :("
	},
	{
		"id": "1368921266875490306",
		"text": "RT @DalaiLama: For most of us, our mother is our first teacher. In my own case, it was my mother who first revealed to me the power of comp\u2026"
	},
	{
		"id": "1488129967573590019",
		"text": "@Henryz_mom Had this exact discussion yesterday with my wife while driving to Madison on 94."
	},
	{
		"id": "145361215307264000",
		"text": "@leoartwall mumbai, india"
	},
	{
		"id": "1488536882237644804",
		"text": "@samponder You and the team do a fantastic job \ud83d\udc4f"
	},
	{
		"id": "1487515585709805571",
		"text": "It's just snow people. It's not magic."
	},
	{
		"id": "12669198660538368",
		"text": "http://goo.gl/rUeeg"
	},
	{
		"id": "1488683357936525314",
		"text": "@ry00751 @Openbordernow I just use LinkedIn or Daijob, I'm looking at Tech Industry roles in Japan though."
	},
	{
		"id": "440290246727450624",
		"text": "Participated in my first Polar Plunge yesterday. 5 degrees and snowing. Great event, benefitting Special Olympics Iowa"
	},
	{
		"id": "1488654513409978369",
		"text": "@NFTLlama roflmao"
	},
	{
		"id": "4896784939",
		"text": "AAAAH, morri. tem DUAS SEMANAS qe eu to sem net vei SEMATA. ent\u00e3o, vou reaprender a usaar o computador e daqui um tempo eu volto bjs"
	},
	{
		"id": "569083483236253696",
		"text": "Read \"Stephen King Revisited\" by @CemeteryDance for FREE here: http://t.co/KJhsoGSuQA -- http://t.co/PFuzoMHLEl"
	},
	{
		"id": "1408044217956438020",
		"text": "@Telemundo51 https://t.co/uoGNxV8HfH"
	},
	{
		"id": "253270345140817920",
		"text": "Hot as FUUUCK http://t.co/lsDaY2Cg"
	},
	{
		"id": "1481037411664556035",
		"text": "@moxie Relevant you web3 point that centralization moves faster than protocols https://t.co/AoWazygKE5"
	},
	{
		"id": "1488601141135003651",
		"text": "RT @tiffany_caban: We should have public snow removal from sidewalks.\n\nCurrently, we are placing undue burdens on pedestrians, especially t\u2026"
	},
	{
		"id": "1487638962701225984",
		"text": "@Drowlerfresheer Al chavocho"
	},
	{
		"id": "1488670122264993799",
		"text": "@artylondon \ud83d\ude31\ud83d\ude35\u200d\ud83d\udcab"
	},
	{
		"id": "80743686119489536",
		"text": "RT @Ubisoft: What were the @FragDolls up to at E3? Hustling like they do to bring you good stuff like this Best of E3 video. Respect. ht ..."
	},
	{
		"id": "1487807528750751748",
		"text": "Note to self - don't start going all crazy with the scissors until the 2nd cup of tea \ud83e\udd26\u200d\u2640\ufe0f https://t.co/obNTxtn03M"
	},
	{
		"id": "156069235343376385",
		"text": "The new Krasnogorsk 3 should be here in a month or two straight from Russia. I have always wanted to shoot on 16mm film. More updates soon."
	},
	{
		"id": "1488570684628512768",
		"text": "RT @dgambacorta: More than 650 Philly police officers are unavailable for duty because of injuries. But some blatantly work second jobs, an\u2026"
	}
]